lzutils/__init__.py
lzutils/cli.py
lzutils-1.4.dist-info/METADATA
lzutils-1.4.dist-info/WHEEL
lzutils-1.4.dist-info/entry_points.txt
lzutils-1.4.dist-info/top_level.txt
lzutils-1.4.dist-info/RECORD
