Metadata-Version: 2.4
Name: lzutils
Version: 1.4
Summary: Simple CLI utility lz
Author: YourName
Requires-Python: >=3.6
Dynamic: author
Dynamic: requires-python
Dynamic: summary
